{
  "Advisor": [
    "Dillard, John G."
  ],
  "Author": [
    "Barton, Thomas F."
  ],
  "Classification": [
    "0488: Chemistry",
    "0996: Geochemistry"
  ],
  "Copyright": [
    "Database copyright ProQuest LLC; ProQuest does not claim copyright in the individual underlying works."
  ],
  "Country of publication": [
    "United States"
  ],
  "Database": "Dissertations & Theses @ Virginia Polytechnic Institute and State University",
  "Degree": [
    "Ph.D."
  ],
  "Document URL": [
    "http://login.ezproxy.lib.vt.edu/login?url=https://search-proquest-com.ezproxy.lib.vt.edu/docview/303924557?accountid=14826"
  ],
  "Document type": [
    "Dissertation/Thesis"
  ],
  "Identifier / keyword": [
    "Pure sciences",
    "Earth sciences"
  ],
  "Language of publication": [
    "English"
  ],
  "Last updated": [
    "2019-10-17"
  ],
  "Number of pages": [
    "171"
  ],
  "Place of publication": [
    "Ann Arbor"
  ],
  "ProQuest document ID": [
    "303924557"
  ],
  "Publication / order number": [
    "9028013"
  ],
  "Publication date": [
    "1990"
  ],
  "Publication title": [
    "ProQuest Dissertations and Theses"
  ],
  "Publication year": [
    "1990"
  ],
  "Publisher": [
    "ProQuest Dissertations Publishing"
  ],
  "School": [
    "Virginia Polytechnic Institute and State University"
  ],
  "School location": [
    "United States -- Virginia"
  ],
  "Section": [
    "0247"
  ],
  "Source type": [
    "Dissertations & Theses"
  ],
  "Subject": [
    "Chemistry",
    "Geochemistry"
  ],
  "Title": "The effect of surface modification on the crystal growth of iron oxides"
}