<?xml version="1.0" encoding="UTF-8"?>
<mets:METS xmlns:mets="http://www.loc.gov/METS/" xmlns:xlink="http://www.w3.org/TR/xlink/" xmlns:xsi="http://www.w3.org/2001/XMLSchema-instance" xmlns:dim="http://www.dspace.org/xmlns/dspace/dim" PROFILE="DSPACE METS SIP Profile 1.0" LABEL="DSpace Item" OBJID="/handle/1721.1/76070" ID="hdl:1721.1/76070" OBJEDIT="/admin/item?itemID=2e6662fd-787e-48b7-be49-351a3e8d09b7">
<mets:dmdSec GROUPID="group_dmd_0" ID="dmd_1">
<mets:mdWrap OTHERMDTYPE="DIM" MDTYPE="OTHER">
<mets:xmlData>
<dim:dim dspaceType="ITEM">
<dim:field qualifier="advisor" mdschema="dc" language="en_US" element="contributor">Frederick J. Adams.</dim:field>
<dim:field qualifier="author" authority="9b90cee52f8f92c83b8b50a4cdb1e468" confidence="UNSET" mdschema="dc" language="en_US" element="contributor">Nez, George</dim:field>
<dim:field qualifier="accessioned" mdschema="dc" element="date">2013-01-07T21:17:59Z</dim:field>
<dim:field qualifier="available" mdschema="dc" element="date">2013-01-07T21:17:59Z</dim:field>
<dim:field qualifier="issued" mdschema="dc" language="en_US" element="date">1950</dim:field>
<dim:field qualifier="uri" mdschema="dc" element="identifier">http://hdl.handle.net/1721.1/76070</dim:field>
<dim:field mdschema="dc" language="en_US" element="description">Thesis (M.C.P.) Massachusetts Institute of Technology. Dept. of Architecture, 1950.</dim:field>
<dim:field qualifier="statementofresponsibility" mdschema="dc" language="en_US" element="description">by George Nez.</dim:field>
<dim:field qualifier="extent" mdschema="dc" language="en_US" element="format">174 leaves</dim:field>
<dim:field qualifier="iso" mdschema="dc" language="en_US" element="language">eng</dim:field>
<dim:field mdschema="dc" language="en_US" element="publisher">Massachusetts Institute of Technology</dim:field>
<dim:field mdschema="dc" language="en_US" element="rights">M.I.T. theses are protected by 
copyright. They may be viewed from this source for any purpose, but 
reproduction or distribution in any format is prohibited without written 
permission. See provided URL for inquiries about permission.</dim:field>
<dim:field qualifier="uri" mdschema="dc" language="en_US" element="rights">http://dspace.mit.edu/handle/1721.1/7582</dim:field>
<dim:field mdschema="dc" language="en_US" element="subject">Architecture</dim:field>
<dim:field mdschema="dc" language="en_US" element="title">Survey and city plan for Keene, N.H.</dim:field>
<dim:field mdschema="dc" language="en_US" element="type">Thesis</dim:field>
<dim:field qualifier="degree" mdschema="dc" language="en_US" element="description">M.C.P.</dim:field>
<dim:field qualifier="department" mdschema="dc" language="en_US" element="contributor">Massachusetts Institute of Technology. Dept. of Architecture</dim:field>
<dim:field qualifier="oclc" mdschema="dc" language="en_US" element="identifier">29945106</dim:field>
</dim:dim>
</mets:xmlData>
</mets:mdWrap>
</mets:dmdSec>
<mets:fileSec>
<mets:fileGrp USE="THUMBNAIL">
<mets:file GROUPID="group_file_31049d46-38ee-43c2-8b45-08a58704e912" CHECKSUM="429ab8f85c04c4a8828de7f0c0ae01b1" MIMETYPE="image/jpeg" SIZE="3061" ID="file_5d49a12e-020e-4a56-ae46-c1dff387fff8" CHECKSUMTYPE="MD5">
<mets:FLocat LOCTYPE="URL" xlink:label="Generated Thumbnail" xlink:href="/bitstream/handle/1721.1/76070/29945106-MIT.pdf.jpg?sequence=5&amp;isAllowed=y" xlink:type="locator" xlink:title="29945106-MIT.pdf.jpg"/>
</mets:file>
</mets:fileGrp>
<mets:fileGrp USE="COVERPAGE"/>
<mets:fileGrp USE="CONTENT">
<mets:file GROUPID="group_file_31049d46-38ee-43c2-8b45-08a58704e912" CHECKSUM="8e10394d73faf61ebd7b4725f533806e" MIMETYPE="application/pdf" SIZE="22641533" ID="file_31049d46-38ee-43c2-8b45-08a58704e912" CHECKSUMTYPE="MD5">
<mets:FLocat LOCTYPE="URL" xlink:label="Full printable version" xlink:href="/bitstream/handle/1721.1/76070/29945106-MIT.pdf?sequence=2&amp;isAllowed=y" xlink:type="locator" xlink:title="29945106-MIT.pdf"/>
</mets:file>
</mets:fileGrp>
<mets:fileGrp USE="TEXT">
<mets:file GROUPID="group_file_31049d46-38ee-43c2-8b45-08a58704e912" CHECKSUM="d65bc6ab16c6c1efcffb10def5e08e08" MIMETYPE="text/plain" SIZE="284915" ID="file_7c985a07-4a3f-4581-8ee1-7de192e99e9a" CHECKSUMTYPE="MD5">
<mets:FLocat LOCTYPE="URL" xlink:label="Extracted text" xlink:href="/bitstream/handle/1721.1/76070/29945106-MIT.pdf.txt?sequence=4&amp;isAllowed=n" xlink:type="locator" xlink:title="29945106-MIT.pdf.txt"/>
</mets:file>
</mets:fileGrp>
</mets:fileSec>
<mets:structMap LABEL="DSpace" TYPE="LOGICAL">
<mets:div DMDID="dmd_1" TYPE="DSpace Item">
<mets:div ID="div_2" TYPE="DSpace Content Bitstream">
<mets:fptr FILEID="file_31049d46-38ee-43c2-8b45-08a58704e912"/>
</mets:div>
</mets:div>
</mets:structMap>
</mets:METS>
