<document><title>NEW APPLICATIONS OF ORGANOMETALLIC REAGENTS IN ORGANIC SYNTHESIS
A STEREOSPECIFIC TOTAL SYNTHESIS OF α-SANTALOL</title>
A thesis presented
by
<author>Herbert Andrew Kirst</author>
to
The Department of <program>Chemistry</program>
in partial fulfillment of the requirements
for the degree of
<degree>Doctor of Philosophy</degree>
in the subject of
Chemistry
<university>Harvard University</university>
Cambridge, Massachusetts
November, <year>1971</year>
Copyright reserved by the author
Reproduced with permission of the copyright owner. Further reproduction prohibited without permission.</document>